odoo/addons/l10n_it_fatturapa_sdicoop/README.rst
odoo/addons/l10n_it_fatturapa_sdicoop/__init__.py
odoo/addons/l10n_it_fatturapa_sdicoop/__manifest__.py
odoo/addons/l10n_it_fatturapa_sdicoop/data/sdi_channel_data.xml
odoo/addons/l10n_it_fatturapa_sdicoop/i18n/it.po
odoo/addons/l10n_it_fatturapa_sdicoop/i18n/l10n_it_fatturapa_sdicoop.pot
odoo/addons/l10n_it_fatturapa_sdicoop/models/__init__.py
odoo/addons/l10n_it_fatturapa_sdicoop/models/sdi_channel.py
odoo/addons/l10n_it_fatturapa_sdicoop/readme/CONTRIBUTORS.rst
odoo/addons/l10n_it_fatturapa_sdicoop/readme/DESCRIPTION.rst
odoo/addons/l10n_it_fatturapa_sdicoop/static/description/icon.png
odoo/addons/l10n_it_fatturapa_sdicoop/static/description/index.html
odoo/addons/l10n_it_fatturapa_sdicoop/tests/__init__.py
odoo/addons/l10n_it_fatturapa_sdicoop/tests/test_account_invoice.py
odoo/addons/l10n_it_fatturapa_sdicoop/tests/test_notification.py
odoo/addons/l10n_it_fatturapa_sdicoop/tests/data/IT05979361218_001.xml
odoo14_addon_l10n_it_fatturapa_sdicoop-14.0.1.0.1.dev5.dist-info/METADATA
odoo14_addon_l10n_it_fatturapa_sdicoop-14.0.1.0.1.dev5.dist-info/WHEEL
odoo14_addon_l10n_it_fatturapa_sdicoop-14.0.1.0.1.dev5.dist-info/top_level.txt
odoo14_addon_l10n_it_fatturapa_sdicoop-14.0.1.0.1.dev5.dist-info/RECORD
