Metadata-Version: 2.1
Name: odoo14-addon-l10n-it-fatturapa-sdicoop
Version: 14.0.1.0.1.dev5
Summary: Invio fatture elettroniche tramite SDICoop
Home-page: https://github.com/OCA/l10n-italy/tree/12.0/l10n_it_fatturapa_sdicoop
Author: TAKOBI, Odoo Community Association (OCA)
Author-email: support@odoo-community.org
License: AGPL-3
Platform: UNKNOWN
Classifier: Programming Language :: Python
Classifier: Framework :: Odoo
Classifier: Framework :: Odoo :: 14.0
Classifier: License :: OSI Approved :: GNU Affero General Public License v3
Requires-Python: >=3.6
Requires-Dist: odoo14-addon-l10n-it-fatturapa-in
Requires-Dist: odoo14-addon-l10n-it-fatturapa-out
Requires-Dist: odoo14-addon-l10n-it-sdi-channel
Requires-Dist: odoo <14.1dev,>=14.0a
